Metadata-Version: 2.1
Name: qgis-plutil
Version: 0.1.1
Summary: A library useful for writing QGis plugins.
Home-page: https://github.com/pyqgis/plutil
Author: Nicu Tofan
Author-email: nicu.tofan@gmail.com
License: MIT
Download-URL: https://github.com/pyqgis/qgis-plutil/archive/v0.1.1.zip
Project-URL: Bug Tracker, https://github.com/pyqgis/qgis-plutil/issues
Project-URL: Documentation, https://readthedocs.org/projects/qgis-plutil/
Project-URL: Source Code, https://github.com/pyqgis/qgis-plutil
Platform: UNKNOWN
Classifier: Development Status :: 3 - Alpha
Classifier: Intended Audience :: Developers
Classifier: License :: OSI Approved :: MIT License
Classifier: Programming Language :: Python
Classifier: Programming Language :: Python :: 3
Classifier: Programming Language :: Python :: 3.6
Classifier: Programming Language :: Python :: Implementation :: CPython
Classifier: Programming Language :: Python :: Implementation :: PyPy
Requires-Python: >=3.6.0
Provides-Extra: tests
Provides-Extra: dev
